LICENSE
README.md
setup.py
deepinfo/__init__.py
deepinfo/density_ratio_estimator.py
deepinfo/divergences.py
deepinfo/mcmc.py
deepinfo.egg-info/PKG-INFO
deepinfo.egg-info/SOURCES.txt
deepinfo.egg-info/dependency_links.txt
deepinfo.egg-info/not-zip-safe
deepinfo.egg-info/requires.txt
deepinfo.egg-info/top_level.txt